justbackoff/__init__.py
justbackoff-0.5.0.dist-info/LICENSE
justbackoff-0.5.0.dist-info/METADATA
justbackoff-0.5.0.dist-info/WHEEL
justbackoff-0.5.0.dist-info/top_level.txt
justbackoff-0.5.0.dist-info/RECORD
