Metadata-Version: 2.1
Name: justbackoff
Version: 0.5.0
Summary: Simple backoff algorithm in Python
Home-page: https://github.com/admiralobvious/justbackoff
Author: Alexandre Ferland
Author-email: aferlandqc@gmail.com
License: MIT
Platform: any
Classifier: Intended Audience :: Developers
Classifier: License :: OSI Approved :: MIT License
Classifier: Operating System :: OS Independent
Classifier: Programming Language :: Python :: 3.5
Classifier: Programming Language :: Python :: 3.6
Classifier: Programming Language :: Python :: 3.7
Classifier: Topic :: Software Development :: Libraries :: Python Modules
